sccomposite/ADT_modality.py
sccomposite/ATAC_modality.py
sccomposite/Multiomics.py
sccomposite/RNA_modality.py
sccomposite/__init__.py
sccomposite/stable_feature_selection.py
sccomposite-1.0.0.dist-info/LICENSE
sccomposite-1.0.0.dist-info/METADATA
sccomposite-1.0.0.dist-info/WHEEL
sccomposite-1.0.0.dist-info/top_level.txt
sccomposite-1.0.0.dist-info/RECORD
