Metadata-Version: 2.1
Name: sccomposite
Version: 1.0.0
Summary: COMPOSITE multiplet detection
Author: Haoran Hu
Author-email: <hah112@pitt.edu>
Keywords: sccomposite,multiplet detection
Classifier: Programming Language :: Python :: 3
Classifier: License :: OSI Approved :: MIT License
Classifier: Operating System :: OS Independent
License-File: LICENSE
